dflock/main.py
dflock/utils.py
dflock-0.1.2.dist-info/licenses/LICENSE
dflock-0.1.2.dist-info/METADATA
dflock-0.1.2.dist-info/WHEEL
dflock-0.1.2.dist-info/entry_points.txt
dflock-0.1.2.dist-info/top_level.txt
dflock-0.1.2.dist-info/RECORD
