Metadata-Version: 2.4
Name: dflock
Version: 0.1.2
Summary: Add your description here
Requires-Python: >=3.10
License-File: LICENSE
Requires-Dist: click>=8.1.8
Dynamic: license-file
